alu/not/not_32.v
module not_32(data_result, data_operandA);
  input [31:0] data_operandA;
  output [31:0] data_result;
  not not_0(data_result[0], data_operandA[0]);
  not not_1(data_result[1], data_operandA[1]);
  not not_2(data_result[2], data_operandA[2]);
  not not_3(data_result[3], data_operandA[3]);
  not not_4(data_result[4], data_operandA[4]);
  not not_5(data_result[5], data_operandA[5]);
  not not_6(data_result[6], data_operandA[6]);
  not not_7(data_result[7], data_operandA[7]);
  not not_8(data_result[8], data_operandA[8]);
  not not_9(data_result[9], data_operandA[9]);
  not not_10(data_result[10], data_operandA[10]);
  not not_11(data_result[11], data_operandA[11]);
  not not_12(data_result[12], data_operandA[12]);
  not not_13(data_result[13], data_operandA[13]);
  not not_14(data_result[14], data_operandA[14]);
  not not_15(data_result[15], data_operandA[15]);
  not not_16(data_result[16], data_operandA[16]);
  not not_17(data_result[17], data_operandA[17]);
  not not_18(data_result[18], data_operandA[18]);
  not not_19(data_result[19], data_operandA[19]);
  not not_20(data_result[20], data_operandA[20]);
  not not_21(data_result[21], data_operandA[21]);
  not not_22(data_result[22], data_operandA[22]);
  not not_23(data_result[23], data_operandA[23]);
  not not_24(data_result[24], data_operandA[24]);
  not not_25(data_result[25], data_operandA[25]);
  not not_26(data_result[26], data_operandA[26]);
  not not_27(data_result[27], data_operandA[27]);
  not not_28(data_result[28], data_operandA[28]);
  not not_29(data_result[29], data_operandA[29]);
  not not_30(data_result[30], data_operandA[30]);
  not not_31(data_result[31], data_operandA[31]);
endmodule

cpu/alu/not/not_32_tb.v
`timescale 1 ns / 100 ps
module not_32_tb;
  wire [31:0] data_operandA;
  wire [31:0] out;
  not_32 not32(out, data_operandA);
  integer i;
  assign data_operandA = i[31:0];

  initial begin
    for (i = 0; i < 1000; i = i + 1) begin
      #20;
      $display("input:%b, output:%b", data_operandA, out);
    end
    $finish;
  end

  initial begin
    $dumpfile("not_32.vcd");
    $dumpvars(0, not_32_tb);
  end
endmodule

alu/not/not_32.vcd
$date
	Wed Jan 25 00:00:38 2023
$end
$version
	Icarus Verilog
$end
$timescale
	100ps
$end
$scope module not_32_tb $end
$var wire 32 ! out [31:0] $end
$var wire 32 " data_operandA [31:0] $end
$var integer 32 # i [31:0] $end
$scope module not32 $end
$var wire 32 $ data_operandA [31:0] $end
$var wire 32 % data_result [31:0] $end
$upscope $end
$upscope $end
$enddefinitions $end
#0
$dumpvars
b11111111111111111111111111111111 %
b0 $
b0 #
b0 "
b11111111111111111111111111111111 !
$end
#200
b11111111111111111111111111111110 !
b11111111111111111111111111111110 %
b1 "
b1 #
b1 $
#400
b11111111111111111111111111111101 !
b11111111111111111111111111111101 %
b10 "
b10 #
b10 $
#600
b11111111111111111111111111111100 !
b11111111111111111111111111111100 %
b11 "
b11 #
b11 $
#800
b11111111111111111111111111111011 !
b11111111111111111111111111111011 %
b100 "
b100 #
b100 $
#1000
b11111111111111111111111111111010 !
b11111111111111111111111111111010 %
b101 "
b101 #
b101 $
#1200
b11111111111111111111111111111001 !
b11111111111111111111111111111001 %
b110 "
b110 #
b110 $
#1400
b11111111111111111111111111111000 !
b11111111111111111111111111111000 %
b111 "
b111 #
b111 $
#1600
b11111111111111111111111111110111 !
b11111111111111111111111111110111 %
b1000 "
b1000 #
b1000 $
#1800
b11111111111111111111111111110110 !
b11111111111111111111111111110110 %
b1001 "
b1001 #
b1001 $
#2000
b11111111111111111111111111110101 !
b11111111111111111111111111110101 %
b1010 "
b1010 #
b1010 $
#2200
b11111111111111111111111111110100 !
b11111111111111111111111111110100 %
b1011 "
b1011 #
b1011 $
#2400
b11111111111111111111111111110011 !
b11111111111111111111111111110011 %
b1100 "
b1100 #
b1100 $
#2600
b11111111111111111111111111110010 !
b11111111111111111111111111110010 %
b1101 "
b1101 #
b1101 $
#2800
b11111111111111111111111111110001 !
b11111111111111111111111111110001 %
b1110 "
b1110 #
b1110 $
#3000
b11111111111111111111111111110000 !
b11111111111111111111111111110000 %
b1111 "
b1111 #
b1111 $
#3200
b11111111111111111111111111101111 !
b11111111111111111111111111101111 %
b10000 "
b10000 #
b10000 $
#3400
b11111111111111111111111111101110 !
b11111111111111111111111111101110 %
b10001 "
b10001 #
b10001 $
#3600
b11111111111111111111111111101101 !
b11111111111111111111111111101101 %
b10010 "
b10010 #
b10010 $
#3800
b11111111111111111111111111101100 !
b11111111111111111111111111101100 %
b10011 "
b10011 #
b10011 $
#4000
b11111111111111111111111111101011 !
b11111111111111111111111111101011 %
b10100 "
b10100 #
b10100 $
#4200
b11111111111111111111111111101010 !
b11111111111111111111111111101010 %
b10101 "
b10101 #
b10101 $
#4400
b11111111111111111111111111101001 !
b11111111111111111111111111101001 %
b10110 "
b10110 #
b10110 $
#4600
b11111111111111111111111111101000 !
b11111111111111111111111111101000 %
b10111 "
b10111 #
b10111 $
#4800
b11111111111111111111111111100111 !
b11111111111111111111111111100111 %
b11000 "
b11000 #
b11000 $
#5000
b11111111111111111111111111100110 !
b11111111111111111111111111100110 %
b11001 "
b11001 #
b11001 $
#5200
b11111111111111111111111111100101 !
b11111111111111111111111111100101 %
b11010 "
b11010 #
b11010 $
#5400
b11111111111111111111111111100100 !
b11111111111111111111111111100100 %
b11011 "
b11011 #
b11011 $
#5600
b11111111111111111111111111100011 !
b11111111111111111111111111100011 %
b11100 "
b11100 #
b11100 $
#5800
b11111111111111111111111111100010 !
b11111111111111111111111111100010 %
b11101 "
b11101 #
b11101 $
#6000
b11111111111111111111111111100001 !
b11111111111111111111111111100001 %
b11110 "
b11110 #
b11110 $
#6200
b11111111111111111111111111100000 !
b11111111111111111111111111100000 %
b11111 "
b11111 #
b11111 $
#6400
b11111111111111111111111111011111 !
b11111111111111111111111111011111 %
b100000 "
b100000 #
b100000 $
#6600
b11111111111111111111111111011110 !
b11111111111111111111111111011110 %
b100001 "
b100001 #
b100001 $
#6800
b11111111111111111111111111011101 !
b11111111111111111111111111011101 %
b100010 "
b100010 #
b100010 $
#7000
b11111111111111111111111111011100 !
b11111111111111111111111111011100 %
b100011 "
b100011 #
b100011 $
#7200
b11111111111111111111111111011011 !
b11111111111111111111111111011011 %
b100100 "
b100100 #
b100100 $
#7400
b11111111111111111111111111011010 !
b11111111111111111111111111011010 %
b100101 "
b100101 #
b100101 $
#7600
b11111111111111111111111111011001 !
b11111111111111111111111111011001 %
b100110 "
b100110 #
b100110 $
#7800
b11111111111111111111111111011000 !
b11111111111111111111111111011000 %
b100111 "
b100111 #
b100111 $
#8000
b11111111111111111111111111010111 !
b11111111111111111111111111010111 %
b101000 "
b101000 #
b101000 $
#8200
b11111111111111111111111111010110 !
b11111111111111111111111111010110 %
b101001 "
b101001 #
b101001 $
#8400
b11111111111111111111111111010101 !
b11111111111111111111111111010101 %
b101010 "
b101010 #
b101010 $
#8600
b11111111111111111111111111010100 !
b11111111111111111111111111010100 %
b101011 "
b101011 #
b101011 $
#8800
b11111111111111111111111111010011 !
b11111111111111111111111111010011 %
b101100 "
b101100 #
b101100 $
#9000
b11111111111111111111111111010010 !
b11111111111111111111111111010010 %
b101101 "
b101101 #
b101101 $
#9200
b11111111111111111111111111010001 !
b11111111111111111111111111010001 %
b101110 "
b101110 #
b101110 $
#9400
b11111111111111111111111111010000 !
b11111111111111111111111111010000 %
b101111 "
b101111 #
b101111 $
#9600
b11111111111111111111111111001111 !
b11111111111111111111111111001111 %
b110000 "
b110000 #
b110000 $
#9800
b11111111111111111111111111001110 !
b11111111111111111111111111001110 %
b110001 "
b110001 #
b110001 $
#10000
b11111111111111111111111111001101 !
b11111111111111111111111111001101 %
b110010 "
b110010 #
b110010 $
#10200
b11111111111111111111111111001100 !
b11111111111111111111111111001100 %
b110011 "
b110011 #
b110011 $
#10400
b11111111111111111111111111001011 !
b11111111111111111111111111001011 %
b110100 "
b110100 #
b110100 $
#10600
b11111111111111111111111111001010 !
b11111111111111111111111111001010 %
b110101 "
b110101 #
b110101 $
#10800
b11111111111111111111111111001001 !
b11111111111111111111111111001001 %
b110110 "
b110110 #
b110110 $
#11000
b11111111111111111111111111001000 !
b11111111111111111111111111001000 %
b110111 "
b110111 #
b110111 $
#11200
b11111111111111111111111111000111 !
b11111111111111111111111111000111 %
b111000 "
b111000 #
b111000 $
#11400
b11111111111111111111111111000110 !
b11111111111111111111111111000110 %
b111001 "
b111001 #
b111001 $
#11600
b11111111111111111111111111000101 !
b11111111111111111111111111000101 %
b111010 "
b111010 #
b111010 $
#11800
b11111111111111111111111111000100 !
b11111111111111111111111111000100 %
b111011 "
b111011 #
b111011 $
#12000
b11111111111111111111111111000011 !
b11111111111111111111111111000011 %
b111100 "
b111100 #
b111100 $
#12200
b11111111111111111111111111000010 !
b11111111111111111111111111000010 %
b111101 "
b111101 #
b111101 $
#12400
b11111111111111111111111111000001 !
b11111111111111111111111111000001 %
b111110 "
b111110 #
b111110 $
#12600
b11111111111111111111111111000000 !
b11111111111111111111111111000000 %
b111111 "
b111111 #
b111111 $
#12800
b11111111111111111111111110111111 !
b11111111111111111111111110111111 %
b1000000 "
b1000000 #
b1000000 $
#13000
b11111111111111111111111110111110 !
b11111111111111111111111110111110 %
b1000001 "
b1000001 #
b1000001 $
#13200
b11111111111111111111111110111101 !
b11111111111111111111111110111101 %
b1000010 "
b1000010 #
b1000010 $
#13400
b11111111111111111111111110111100 !
b11111111111111111111111110111100 %
b1000011 "
b1000011 #
b1000011 $
#13600
b11111111111111111111111110111011 !
b11111111111111111111111110111011 %
b1000100 "
b1000100 #
b1000100 $
#13800
b11111111111111111111111110111010 !
b11111111111111111111111110111010 %
b1000101 "
b1000101 #
b1000101 $
#14000
b11111111111111111111111110111001 !
b11111111111111111111111110111001 %
b1000110 "
b1000110 #
b1000110 $
#14200
b11111111111111111111111110111000 !
b11111111111111111111111110111000 %
b1000111 "
b1000111 #
b1000111 $
#14400
b11111111111111111111111110110111 !
b11111111111111111111111110110111 %
b1001000 "
b1001000 #
b1001000 $
#14600
b11111111111111111111111110110110 !
b11111111111111111111111110110110 %
b1001001 "
b1001001 #
b1001001 $
#14800
b11111111111111111111111110110101 !
b11111111111111111111111110110101 %
b1001010 "
b1001010 #
b1001010 $
#15000
b11111111111111111111111110110100 !
b11111111111111111111111110110100 %
b1001011 "
b1001011 #
b1001011 $
#15200
b11111111111111111111111110110011 !
b11111111111111111111111110110011 %
b1001100 "
b1001100 #
b1001100 $
#15400
b11111111111111111111111110110010 !
b11111111111111111111111110110010 %
b1001101 "
b1001101 #
b1001101 $
#15600
b11111111111111111111111110110001 !
b11111111111111111111111110110001 %
b1001110 "
b1001110 #
b1001110 $
#15800
b11111111111111111111111110110000 !
b11111111111111111111111110110000 %
b1001111 "
b1001111 #
b1001111 $
#16000
b11111111111111111111111110101111 !
b11111111111111111111111110101111 %
b1010000 "
b1010000 #
b1010000 $
#16200
b11111111111111111111111110101110 !
b11111111111111111111111110101110 %
b1010001 "
b1010001 #
b1010001 $
#16400
b11111111111111111111111110101101 !
b11111111111111111111111110101101 %
b1010010 "
b1010010 #
b1010010 $
#16600
b11111111111111111111111110101100 !
b11111111111111111111111110101100 %
b1010011 "
b1010011 #
b1010011 $
#16800
b11111111111111111111111110101011 !
b11111111111111111111111110101011 %
b1010100 "
b1010100 #
b1010100 $
#17000
b11111111111111111111111110101010 !
b11111111111111111111111110101010 %
b1010101 "
b1010101 #
b1010101 $
#17200
b11111111111111111111111110101001 !
b11111111111111111111111110101001 %
b1010110 "
b1010110 #
b1010110 $
#17400
b11111111111111111111111110101000 !
b11111111111111111111111110101000 %
b1010111 "
b1010111 #
b1010111 $
#17600
b11111111111111111111111110100111 !
b11111111111111111111111110100111 %
b1011000 "
b1011000 #
b1011000 $
#17800
b11111111111111111111111110100110 !
b11111111111111111111111110100110 %
b1011001 "
b1011001 #
b1011001 $
#18000
b11111111111111111111111110100101 !
b11111111111111111111111110100101 %
b1011010 "
b1011010 #
b1011010 $
#18200
b11111111111111111111111110100100 !
b11111111111111111111111110100100 %
b1011011 "
b1011011 #
b1011011 $
#18400
b11111111111111111111111110100011 !
b11111111111111111111111110100011 %
b1011100 "
b1011100 #
b1011100 $
#18600
b11111111111111111111111110100010 !
b11111111111111111111111110100010 %
b1011101 "
b1011101 #
b1011101 $
#18800
b11111111111111111111111110100001 !
b11111111111111111111111110100001 %
b1011110 "
b1011110 #
b1011110 $
#19000
b11111111111111111111111110100000 !
b11111111111111111111111110100000 %
b1011111 "
b1011111 #
b1011111 $
#19200
b11111111111111111111111110011111 !
b11111111111111111111111110011111 %
b1100000 "
b1100000 #
b1100000 $
#19400
b11111111111111111111111110011110 !
b11111111111111111111111110011110 %
b1100001 "
b1100001 #
b1100001 $
#19600
b11111111111111111111111110011101 !
b11111111111111111111111110011101 %
b1100010 "
b1100010 #
b1100010 $
#19800
b11111111111111111111111110011100 !
b11111111111111111111111110011100 %
b1100011 "
b1100011 #
b1100011 $
#20000
b11111111111111111111111110011011 !
b11111111111111111111111110011011 %
b1100100 "
b1100100 #
b1100100 $
#20200
b11111111111111111111111110011010 !
b11111111111111111111111110011010 %
b1100101 "
b1100101 #
b1100101 $
#20400
b11111111111111111111111110011001 !
b11111111111111111111111110011001 %
b1100110 "
b1100110 #
b1100110 $
#20600
b11111111111111111111111110011000 !
b11111111111111111111111110011000 %
b1100111 "
b1100111 #
b1100111 $
#20800
b11111111111111111111111110010111 !
b11111111111111111111111110010111 %
b1101000 "
b1101000 #
b1101000 $
#21000
b11111111111111111111111110010110 !
b11111111111111111111111110010110 %
b1101001 "
b1101001 #
b1101001 $
#21200
b11111111111111111111111110010101 !
b11111111111111111111111110010101 %
b1101010 "
b1101010 #
b1101010 $
#21400
b11111111111111111111111110010100 !
b11111111111111111111111110010100 %
b1101011 "
b1101011 #
b1101011 $
#21600
b11111111111111111111111110010011 !
b11111111111111111111111110010011 %
b1101100 "
b1101100 #
b1101100 $
#21800
b11111111111111111111111110010010 !
b11111111111111111111111110010010 %
b1101101 "
b1101101 #
b1101101 $
#22000
b11111111111111111111111110010001 !
b11111111111111111111111110010001 %
b1101110 "
b1101110 #
b1101110 $
#22200
b11111111111111111111111110010000 !
b11111111111111111111111110010000 %
b1101111 "
b1101111 #
b1101111 $
#22400
b11111111111111111111111110001111 !
b11111111111111111111111110001111 %
b1110000 "
b1110000 #
b1110000 $
#22600
b11111111111111111111111110001110 !
b11111111111111111111111110001110 %
b1110001 "
b1110001 #
b1110001 $
#22800
b11111111111111111111111110001101 !
b11111111111111111111111110001101 %
b1110010 "
b1110010 #
b1110010 $
#23000
b11111111111111111111111110001100 !
b11111111111111111111111110001100 %
b1110011 "
b1110011 #
b1110011 $
#23200
b11111111111111111111111110001011 !
b11111111111111111111111110001011 %
b1110100 "
b1110100 #
b1110100 $
#23400
b11111111111111111111111110001010 !
b11111111111111111111111110001010 %
b1110101 "
b1110101 #
b1110101 $
#23600
b11111111111111111111111110001001 !
b11111111111111111111111110001001 %
b1110110 "
b1110110 #
b1110110 $
#23800
b11111111111111111111111110001000 !
b11111111111111111111111110001000 %
b1110111 "
b1110111 #
b1110111 $
#24000
b11111111111111111111111110000111 !
b11111111111111111111111110000111 %
b1111000 "
b1111000 #
b1111000 $
#24200
b11111111111111111111111110000110 !
b11111111111111111111111110000110 %
b1111001 "
b1111001 #
b1111001 $
#24400
b11111111111111111111111110000101 !
b11111111111111111111111110000101 %
b1111010 "
b1111010 #
b1111010 $
#24600
b11111111111111111111111110000100 !
b11111111111111111111111110000100 %
b1111011 "
b1111011 #
b1111011 $
#24800
b11111111111111111111111110000011 !
b11111111111111111111111110000011 %
b1111100 "
b1111100 #
b1111100 $
#25000
b11111111111111111111111110000010 !
b11111111111111111111111110000010 %
b1111101 "
b1111101 #
b1111101 $
#25200
b11111111111111111111111110000001 !
b11111111111111111111111110000001 %
b1111110 "
b1111110 #
b1111110 $
#25400
b11111111111111111111111110000000 !
b11111111111111111111111110000000 %
b1111111 "
b1111111 #
b1111111 $
#25600
b11111111111111111111111101111111 !
b11111111111111111111111101111111 %
b10000000 "
b10000000 #
b10000000 $
#25800
b11111111111111111111111101111110 !
b11111111111111111111111101111110 %
b10000001 "
b10000001 #
b10000001 $
#26000
b11111111111111111111111101111101 !
b11111111111111111111111101111101 %
b10000010 "
b10000010 #
b10000010 $
#26200
b11111111111111111111111101111100 !
b11111111111111111111111101111100 %
b10000011 "
b10000011 #
b10000011 $
#26400
b11111111111111111111111101111011 !
b11111111111111111111111101111011 %
b10000100 "
b10000100 #
b10000100 $
#26600
b11111111111111111111111101111010 !
b11111111111111111111111101111010 %
b10000101 "
b10000101 #
b10000101 $
#26800
b11111111111111111111111101111001 !
b11111111111111111111111101111001 %
b10000110 "
b10000110 #
b10000110 $
#27000
b11111111111111111111111101111000 !
b11111111111111111111111101111000 %
b10000111 "
b10000111 #
b10000111 $
#27200
b11111111111111111111111101110111 !
b11111111111111111111111101110111 %
b10001000 "
b10001000 #
b10001000 $
#27400
b11111111111111111111111101110110 !
b11111111111111111111111101110110 %
b10001001 "
b10001001 #
b10001001 $
#27600
b11111111111111111111111101110101 !
b11111111111111111111111101110101 %
b10001010 "
b10001010 #
b10001010 $
#27800
b11111111111111111111111101110100 !
b11111111111111111111111101110100 %
b10001011 "
b10001011 #
b10001011 $
#28000
b11111111111111111111111101110011 !
b11111111111111111111111101110011 %
b10001100 "
b10001100 #
b10001100 $
#28200
b11111111111111111111111101110010 !
b11111111111111111111111101110010 %
b10001101 "
b10001101 #
b10001101 $
#28400
b11111111111111111111111101110001 !
b11111111111111111111111101110001 %
b10001110 "
b10001110 #
b10001110 $
#28600
b11111111111111111111111101110000 !
b11111111111111111111111101110000 %
b10001111 "
b10001111 #
b10001111 $
#28800
b11111111111111111111111101101111 !
b11111111111111111111111101101111 %
b10010000 "
b10010000 #
b10010000 $
#29000
b11111111111111111111111101101110 !
b11111111111111111111111101101110 %
b10010001 "
b10010001 #
b10010001 $
#29200
b11111111111111111111111101101101 !
b11111111111111111111111101101101 %
b10010010 "
b10010010 #
b10010010 $
#29400
b11111111111111111111111101101100 !
b11111111111111111111111101101100 %
b10010011 "
b10010011 #
b10010011 $
#29600
b11111111111111111111111101101011 !
b11111111111111111111111101101011 %
b10010100 "
b10010100 #
b10010100 $
#29800
b11111111111111111111111101101010 !
b11111111111111111111111101101010 %
b10010101 "
b10010101 #
b10010101 $
#30000
b11111111111111111111111101101001 !
b11111111111111111111111101101001 %
b10010110 "
b10010110 #
b10010110 $
#30200
b11111111111111111111111101101000 !
b11111111111111111111111101101000 %
b10010111 "
b10010111 #
b10010111 $
#30400
b11111111111111111111111101100111 !
b11111111111111111111111101100111 %
b10011000 "
b10011000 #
b10011000 $
#30600
b11111111111111111111111101100110 !
b11111111111111111111111101100110 %
b10011001 "
b10011001 #
b10011001 $
#30800
b11111111111111111111111101100101 !
b11111111111111111111111101100101 %
b10011010 "
b10011010 #
b10011010 $
#31000
b11111111111111111111111101100100 !
b11111111111111111111111101100100 %
b10011011 "
b10011011 #
b10011011 $
#31200
b11111111111111111111111101100011 !
b11111111111111111111111101100011 %
b10011100 "
b10011100 #
b10011100 $
#31400
b11111111111111111111111101100010 !
b11111111111111111111111101100010 %
b10011101 "
b10011101 #
b10011101 $
#31600
b11111111111111111111111101100001 !
b11111111111111111111111101100001 %
b10011110 "
b10011110 #
b10011110 $
#31800
b11111111111111111111111101100000 !
b11111111111111111111111101100000 %
b10011111 "
b10011111 #
b10011111 $
#32000
b11111111111111111111111101011111 !
b11111111111111111111111101011111 %
b10100000 "
b10100000 #
b10100000 $
#32200
b11111111111111111111111101011110 !
b11111111111111111111111101011110 %
b10100001 "
b10100001 #
b10100001 $
#32400
b11111111111111111111111101011101 !
b11111111111111111111111101011101 %
b10100010 "
b10100010 #
b10100010 $
#32600
b11111111111111111111111101011100 !
b11111111111111111111111101011100 %
b10100011 "
b10100011 #
b10100011 $
#32800
b11111111111111111111111101011011 !
b11111111111111111111111101011011 %
b10100100 "
b10100100 #
b10100100 $
#33000
b11111111111111111111111101011010 !
b11111111111111111111111101011010 %
b10100101 "
b10100101 #
b10100101 $
#33200
b11111111111111111111111101011001 !
b11111111111111111111111101011001 %
b10100110 "
b10100110 #
b10100110 $
#33400
b11111111111111111111111101011000 !
b11111111111111111111111101011000 %
b10100111 "
b10100111 #
b10100111 $
#33600
b11111111111111111111111101010111 !
b11111111111111111111111101010111 %
b10101000 "
b10101000 #
b10101000 $
#33800
b11111111111111111111111101010110 !
b11111111111111111111111101010110 %
b10101001 "
b10101001 #
b10101001 $
#34000
b11111111111111111111111101010101 !
b11111111111111111111111101010101 %
b10101010 "
b10101010 #
b10101010 $
#34200
b11111111111111111111111101010100 !
b11111111111111111111111101010100 %
b10101011 "
b10101011 #
b10101011 $
#34400
b11111111111111111111111101010011 !
b11111111111111111111111101010011 %
b10101100 "
b10101100 #
b10101100 $
#34600
b11111111111111111111111101010010 !
b11111111111111111111111101010010 %
b10101101 "
b10101101 #
b10101101 $
#34800
b11111111111111111111111101010001 !
b11111111111111111111111101010001 %
b10101110 "
b10101110 #
b10101110 $
#35000
b11111111111111111111111101010000 !
b11111111111111111111111101010000 %
b10101111 "
b10101111 #
b10101111 $
#35200
b11111111111111111111111101001111 !
b11111111111111111111111101001111 %
b10110000 "
b10110000 #
b10110000 $
#35400
b11111111111111111111111101001110 !
b11111111111111111111111101001110 %
b10110001 "
b10110001 #
b10110001 $
#35600
b11111111111111111111111101001101 !
b11111111111111111111111101001101 %
b10110010 "
b10110010 #
b10110010 $
#35800
b11111111111111111111111101001100 !
b11111111111111111111111101001100 %
b10110011 "
b10110011 #
b10110011 $
#36000
b11111111111111111111111101001011 !
b11111111111111111111111101001011 %
b10110100 "
b10110100 #
b10110100 $
#36200
b11111111111111111111111101001010 !
b11111111111111111111111101001010 %
b10110101 "
b10110101 #
b10110101 $
#36400
b11111111111111111111111101001001 !
b11111111111111111111111101001001 %
b10110110 "
b10110110 #
b10110110 $
#36600
b11111111111111111111111101001000 !
b11111111111111111111111101001000 %
b10110111 "
b10110111 #
b10110111 $
#36800
b11111111111111111111111101000111 !
b11111111111111111111111101000111 %
b10111000 "
b10111000 #
b10111000 $
#37000
b11111111111111111111111101000110 !
b11111111111111111111111101000110 %
b10111001 "
b10111001 #
b10111001 $
#37200
b11111111111111111111111101000101 !
b11111111111111111111111101000101 %
b10111010 "
b10111010 #
b10111010 $
#37400
b11111111111111111111111101000100 !
b11111111111111111111111101000100 %
b10111011 "
b10111011 #
b10111011 $
#37600
b11111111111111111111111101000011 !
b11111111111111111111111101000011 %
b10111100 "
b10111100 #
b10111100 $
#37800
b11111111111111111111111101000010 !
b11111111111111111111111101000010 %
b10111101 "
b10111101 #
b10111101 $
#38000
b11111111111111111111111101000001 !
b11111111111111111111111101000001 %
b10111110 "
b10111110 #
b10111110 $
#38200
b11111111111111111111111101000000 !
b11111111111111111111111101000000 %
b10111111 "
b10111111 #
b10111111 $
#38400
b11111111111111111111111100111111 !
b11111111111111111111111100111111 %
b11000000 "
b11000000 #
b11000000 $
#38600
b11111111111111111111111100111110 !
b11111111111111111111111100111110 %
b11000001 "
b11000001 #
b11000001 $
#38800
b11111111111111111111111100111101 !
b11111111111111111111111100111101 %
b11000010 "
b11000010 #
b11000010 $
#39000
b11111111111111111111111100111100 !
b11111111111111111111111100111100 %
b11000011 "
b11000011 #
b11000011 $
#39200
b11111111111111111111111100111011 !
b11111111111111111111111100111011 %
b11000100 "
b11000100 #
b11000100 $
#39400
b11111111111111111111111100111010 !
b11111111111111111111111100111010 %
b11000101 "
b11000101 #
b11000101 $
#39600
b11111111111111111111111100111001 !
b11111111111111111111111100111001 %
b11000110 "
b11000110 #
b11000110 $
#39800
b11111111111111111111111100111000 !
b11111111111111111111111100111000 %
b11000111 "
b11000111 #
b11000111 $
#40000
b11111111111111111111111100110111 !
b11111111111111111111111100110111 %
b11001000 "
b11001000 #
b11001000 $
#40200
b11111111111111111111111100110110 !
b11111111111111111111111100110110 %
b11001001 "
b11001001 #
b11001001 $
#40400
b11111111111111111111111100110101 !
b11111111111111111111111100110101 %
b11001010 "
b11001010 #
b11001010 $
#40600
b11111111111111111111111100110100 !
b11111111111111111111111100110100 %
b11001011 "
b11001011 #
b11001011 $
#40800
b11111111111111111111111100110011 !
b11111111111111111111111100110011 %
b11001100 "
b11001100 #
b11001100 $
#41000
b11111111111111111111111100110010 !
b11111111111111111111111100110010 %
b11001101 "
b11001101 #
b11001101 $
#41200
b11111111111111111111111100110001 !
b11111111111111111111111100110001 %
b11001110 "
b11001110 #
b11001110 $
#41400
b11111111111111111111111100110000 !
b11111111111111111111111100110000 %
b11001111 "
b11001111 #
b11001111 $
#41600
b11111111111111111111111100101111 !
b11111111111111111111111100101111 %
b11010000 "
b11010000 #
b11010000 $
#41800
b11111111111111111111111100101110 !
b11111111111111111111111100101110 %
b11010001 "
b11010001 #
b11010001 $
#42000
b11111111111111111111111100101101 !
b11111111111111111111111100101101 %
b11010010 "
b11010010 #
b11010010 $
#42200
b11111111111111111111111100101100 !
b11111111111111111111111100101100 %
b11010011 "
b11010011 #
b11010011 $
#42400
b11111111111111111111111100101011 !
b11111111111111111111111100101011 %
b11010100 "
b11010100 #
b11010100 $
#42600
b11111111111111111111111100101010 !
b11111111111111111111111100101010 %
b11010101 "
b11010101 #
b11010101 $
#42800
b11111111111111111111111100101001 !
b11111111111111111111111100101001 %
b11010110 "
b11010110 #
b11010110 $
#43000
b11111111111111111111111100101000 !
b11111111111111111111111100101000 %
b11010111 "
b11010111 #
b11010111 $
#43200
b11111111111111111111111100100111 !
b11111111111111111111111100100111 %
b11011000 "
b11011000 #
b11011000 $
#43400
b11111111111111111111111100100110 !
b11111111111111111111111100100110 %
b11011001 "
b11011001 #
b11011001 $
#43600
b11111111111111111111111100100101 !
b11111111111111111111111100100101 %
b11011010 "
b11011010 #
b11011010 $
#43800
b11111111111111111111111100100100 !
b11111111111111111111111100100100 %
b11011011 "
b11011011 #
b11011011 $
#44000
b11111111111111111111111100100011 !
b11111111111111111111111100100011 %
b11011100 "
b11011100 #
b11011100 $
#44200
b11111111111111111111111100100010 !
b11111111111111111111111100100010 %
b11011101 "
b11011101 #
b11011101 $
#44400
b11111111111111111111111100100001 !
b11111111111111111111111100100001 %
b11011110 "
b11011110 #
b11011110 $
#44600
b11111111111111111111111100100000 !
b11111111111111111111111100100000 %
b11011111 "
b11011111 #
b11011111 $
#44800
b11111111111111111111111100011111 !
b11111111111111111111111100011111 %
b11100000 "
b11100000 #
b11100000 $
#45000
b11111111111111111111111100011110 !
b11111111111111111111111100011110 %
b11100001 "
b11100001 #
b11100001 $
#45200
b11111111111111111111111100011101 !
b11111111111111111111111100011101 %
b11100010 "
b11100010 #
b11100010 $
#45400
b11111111111111111111111100011100 !
b11111111111111111111111100011100 %
b11100011 "
b11100011 #
b11100011 $
#45600
b11111111111111111111111100011011 !
b11111111111111111111111100011011 %
b11100100 "
b11100100 #
b11100100 $
#45800
b11111111111111111111111100011010 !
b11111111111111111111111100011010 %
b11100101 "
b11100101 #
b11100101 $
#46000
b11111111111111111111111100011001 !
b11111111111111111111111100011001 %
b11100110 "
b11100110 #
b11100110 $
#46200
b11111111111111111111111100011000 !
b11111111111111111111111100011000 %
b11100111 "
b11100111 #
b11100111 $
#46400
b11111111111111111111111100010111 !
b11111111111111111111111100010111 %
b11101000 "
b11101000 #
b11101000 $
#46600
b11111111111111111111111100010110 !
b11111111111111111111111100010110 %
b11101001 "
b11101001 #
b11101001 $
#46800
b11111111111111111111111100010101 !
b11111111111111111111111100010101 %
b11101010 "
b11101010 #
b11101010 $
#47000
b11111111111111111111111100010100 !
b11111111111111111111111100010100 %
b11101011 "
b11101011 #
b11101011 $
#47200
b11111111111111111111111100010011 !
b11111111111111111111111100010011 %
b11101100 "
b11101100 #
b11101100 $
#47400
b11111111111111111111111100010010 !
b11111111111111111111111100010010 %
b11101101 "
b11101101 #
b11101101 $
#47600
b11111111111111111111111100010001 !
b11111111111111111111111100010001 %
b11101110 "
b11101110 #
b11101110 $
#47800
b11111111111111111111111100010000 !
b11111111111111111111111100010000 %
b11101111 "
b11101111 #
b11101111 $
#48000
b11111111111111111111111100001111 !
b11111111111111111111111100001111 %
b11110000 "
b11110000 #
b11110000 $
#48200
b11111111111111111111111100001110 !
b11111111111111111111111100001110 %
b11110001 "
b11110001 #
b11110001 $
#48400
b11111111111111111111111100001101 !
b11111111111111111111111100001101 %
b11110010 "
b11110010 #
b11110010 $
#48600
b11111111111111111111111100001100 !
b11111111111111111111111100001100 %
b11110011 "
b11110011 #
b11110011 $
#48800
b11111111111111111111111100001011 !
b11111111111111111111111100001011 %
b11110100 "
b11110100 #
b11110100 $
#49000
b11111111111111111111111100001010 !
b11111111111111111111111100001010 %
b11110101 "
b11110101 #
b11110101 $
#49200
b11111111111111111111111100001001 !
b11111111111111111111111100001001 %
b11110110 "
b11110110 #
b11110110 $
#49400
b11111111111111111111111100001000 !
b11111111111111111111111100001000 %
b11110111 "
b11110111 #
b11110111 $
#49600
b11111111111111111111111100000111 !
b11111111111111111111111100000111 %
b11111000 "
b11111000 #
b11111000 $
#49800
b11111111111111111111111100000110 !
b11111111111111111111111100000110 %
b11111001 "
b11111001 #
b11111001 $
#50000
b11111111111111111111111100000101 !
b11111111111111111111111100000101 %
b11111010 "
b11111010 #
b11111010 $
#50200
b11111111111111111111111100000100 !
b11111111111111111111111100000100 %
b11111011 "
b11111011 #
b11111011 $
#50400
b11111111111111111111111100000011 !
b11111111111111111111111100000011 %
b11111100 "
b11111100 #
b11111100 $
#50600
b11111111111111111111111100000010 !
b11111111111111111111111100000010 %
b11111101 "
b11111101 #
b11111101 $
