Lab2/one_bit_adder.v
module one_bit_adder(S, Cout, A, B, Cin);
  input A, B, Cin;
  output S, Cout;
  wire w0, w1, w2, w3, w4, w5, w6
  nand n0(w0, A, B);
  nand n1(w1, A, w0);
  nand n2(w2, w0, B);
  nand n3(w3, w1, w2);
  nand n4(w4, w3, Cin);
  nand n5(w5, w3, w4);
  nand n6(w6, w4, Cin);
  nand n7(Cout, w4, w0);
  nand n8(S, w5, w6);
endmodule

Lab2/one_bit_adder_tb.v
`timescale 1 ns / 100 ps
module one_bit_adder_tb;
  reg A, B, Cin;
  wire S, Cout;

  one_bit_adder adder(.A(A), .B(B), .Cin(Cin), .S(S), .Cout(Cout));
  initial begin
    A = 0;
    B = 0;
    Cin = 0;
    #80;
    $finish;
  end
  always 
    #10 A = ~A;
  always 
    #20 B = ~B;
  always 
    #40 Cin = ~Cin;
    
  always @(A, B, Cin) begin
    #1;
    $display("A:%b, B:%b, Cin:%b => S:%b, Cout:%b", A, B, Cin, S, Cout);
  end

  initial begin
    $dumpfile("one_bit_adder.vcd");
    $dumpvars(0, one_bit_adder_tb);
  end

endmodule

Lab2/one_bit_adder.vcd
$date
	Tue Jan 24 15:54:40 2023
$end
$version
	Icarus Verilog
$end
$timescale
	100ps
$end
$scope module one_bit_adder_tb $end
$var wire 1 ! S $end
$var wire 1 " Cout $end
$var reg 1 # A $end
$var reg 1 $ B $end
$var reg 1 % Cin $end
$scope module adder $end
$var wire 1 # A $end
$var wire 1 $ B $end
$var wire 1 % Cin $end
$var wire 1 " Cout $end
$var wire 1 ! S $end
$var wire 1 & w0 $end
$var wire 1 ' w1 $end
$var wire 1 ( w2 $end
$var wire 1 ) w3 $end
$var wire 1 * w4 $end
$var wire 1 + w5 $end
$var wire 1 , w6 $end
$upscope $end
$upscope $end
$enddefinitions $end
#0
$dumpvars
1,
1+
1*
0)
1(
1'
1&
0%
0$
0#
0"
0!
$end
#100
1!
0+
1)
0'
1#
#200
1'
0(
0#
1$
#300
0!
1+
0)
1(
1"
0&
1'
1#
#400
0"
1!
1&
0,
0#
0$
1%
#500
0!
1,
1"
0*
1+
1)
0'
1#
#600
1'
0(
0#
1$
#700
1!
0,
1*
0)
1(
0&
1'
1#
#800
0"
0!
1&
1,
0#
0$
0%
