Lab3/mux_2.v
module mux_2(out, select, in0, in1);
input select;
input in0, in1;
output out;
assign out = select ? in1 : in0;
endmodule

Lab3/mux_4.v
module mux_4(out, select, in0, in1, in2, in3);
  input [1:0] select;
  input in0, in1, in2, in3;
  output out;
  wire w1, w2;
  mux_2 first_top(w1, select[0], in0, in1);
  mux_2 first_bottom(w2, select[0], in2, in3);
  mux_2 second(out, select[1], w1, w2);
endmodule

Lab3/mux_8.v
module mux_8(out, select, in0, in1, in2, in3, in4, in5, in6, in7);
  input [2:0] select;
  input in0, in1, in2, in3, in4, in5, in6, in7;
  output out;
  wire w1, w2;
  mux_4 mux1(w1, select[1:0], in0, in1, in2, in3);
  mux_4 mux2(w2, select[1:0], in4, in5, in6, in7);
  mux_2 mux3(out, select[2], w1, w2);
endmodule

Lab3/two_bit_comparator.v
module two_bit_comparator(preEQ, preGT, A, B, EQ, GT);
  input preEQ, preGT;
  input [1:0] A, B;
  output EQ, GT;
  wire [2:0] select;
  assign select[2:1] = A;
  assign select[0] = B[1];
  wire notB0, GT_out, EQ_out;
  not not_B0(notB0, B[0]);
  mux_2 GT_select(GT, preEQ, preGT, GT_out);
  mux_8 GT_mux(GT_out, select, 0, 0, notB0, 0, 1, 0, 1, notB0);
  mux_2 EQ_select(EQ, preEQ, 0, EQ_out);
  mux_8 EQ_mux(EQ_out, select, notB0, 0, B[0], 0, 0, notB0, 0, B[0]);
endmodule

Lab3/eight_comparator.v
module eight_comparator(preEQ, preGT, A, B, EQ, GT);
  input [7:0] A, B;
  input preEQ, preGT;
  output EQ, GT;

  wire EQ3, EQ2, EQ1, EQ0, GT3, GT2, GT1, GT0;

  two_bit_comparator comp3(preEQ, preGT, A[7:6], B[7:6], EQ3, GT3);
  two_bit_comparator comp2(EQ3, GT3, A[5:4], B[5:4], EQ2, GT2);
  two_bit_comparator comp1(EQ2, GT2, A[3:2], B[3:2], EQ1, GT1);
  two_bit_comparator comp0(EQ1, GT1, A[1:0], B[1:0], EQ, GT);
endmodule

Lab3/eight_comparator_tb.v
`timescale 1 ns / 100 ps
module eight_comparator_tb;
  wire [7:0] A, B;
  wire preEQ, preGT, EQ, GT;
  eight_comparator comp(preEQ, preGT, A, B, EQ, GT);
  integer i;
  integer j;
  integer k;
  assign A = i[7:0];
  assign B = j[7:0];
  assign {preEQ, preGT} = k[1:0];

  initial begin
    // for (i = 0; i < 4; i = i + 1) begin
    //   #20;
    //   $display("preEQ:%b, preGT:%b, A:%b, B:%b, EQ:%b, GT:%b", preEQ, preGT, A, B, EQ, GT, );
    // end
    assign i = 185;
    assign j = 185;
    for (k = 0; k < 4; k = k + 1) begin
      #20;
      $display("preEQ:%b, preGT:%b, A:%b, B:%b, EQ:%b, GT:%b", preEQ, preGT, A, B, EQ, GT, );
    end
    #20;
    assign i = 195;
    assign j = 163;
    for (k = 0; k < 4; k = k + 1) begin
      #20;
      $display("preEQ:%b, preGT:%b, A:%b, B:%b, EQ:%b, GT:%b", preEQ, preGT, A, B, EQ, GT, );
    end
    #20;
    assign i = 25;
    assign j = 85;
    for (k = 0; k < 4; k = k + 1) begin
      #20;
      $display("preEQ:%b, preGT:%b, A:%b, B:%b, EQ:%b, GT:%b", preEQ, preGT, A, B, EQ, GT, );
    end
    #20;
    $finish;
  end

  initial begin
    $dumpfile("eight_comparator.vcd");
    $dumpvars(0, eight_comparator_tb);
  end
endmodule

Lab3/eight_comparator.vcd
$date
	Tue Jan 31 16:37:07 2023
$end
$version
	Icarus Verilog
$end
$timescale
	100ps
$end
$scope module eight_comparator_tb $end
$var wire 1 ! preGT $end
$var wire 1 " preEQ $end
$var wire 1 # GT $end
$var wire 1 $ EQ $end
$var wire 8 % B [7:0] $end
$var wire 8 & A [7:0] $end
$var integer 32 ' i [31:0] $end
$var integer 32 ( j [31:0] $end
$var integer 32 ) k [31:0] $end
$scope module comp $end
$var wire 8 * A [7:0] $end
$var wire 8 + B [7:0] $end
$var wire 1 " preEQ $end
$var wire 1 ! preGT $end
$var wire 1 , GT3 $end
$var wire 1 - GT2 $end
$var wire 1 . GT1 $end
$var wire 1 # GT $end
$var wire 1 / EQ3 $end
$var wire 1 0 EQ2 $end
$var wire 1 1 EQ1 $end
$var wire 1 $ EQ $end
$scope module comp0 $end
$var wire 2 2 A [1:0] $end
$var wire 2 3 B [1:0] $end
$var wire 1 4 notB0 $end
$var wire 3 5 select [2:0] $end
$var wire 1 . preGT $end
$var wire 1 1 preEQ $end
$var wire 1 6 GT_out $end
$var wire 1 # GT $end
$var wire 1 7 EQ_out $end
$var wire 1 $ EQ $end
$scope module EQ_mux $end
$var wire 1 4 in0 $end
$var wire 1 8 in1 $end
$var wire 1 9 in2 $end
$var wire 1 : in3 $end
$var wire 1 ; in4 $end
$var wire 1 4 in5 $end
$var wire 1 < in6 $end
$var wire 1 = in7 $end
$var wire 3 > select [2:0] $end
$var wire 1 ? w2 $end
$var wire 1 @ w1 $end
$var wire 1 7 out $end
$scope module mux1 $end
$var wire 1 4 in0 $end
$var wire 1 8 in1 $end
$var wire 1 9 in2 $end
$var wire 1 : in3 $end
$var wire 2 A select [1:0] $end
$var wire 1 B w2 $end
$var wire 1 C w1 $end
$var wire 1 @ out $end
$scope module first_bottom $end
$var wire 1 9 in0 $end
$var wire 1 : in1 $end
$var wire 1 D select $end
$var wire 1 B out $end
$upscope $end
$scope module first_top $end
$var wire 1 4 in0 $end
$var wire 1 8 in1 $end
$var wire 1 E select $end
$var wire 1 C out $end
$upscope $end
$scope module second $end
$var wire 1 C in0 $end
$var wire 1 B in1 $end
$var wire 1 F select $end
$var wire 1 @ out $end
$upscope $end
$upscope $end
$scope module mux2 $end
$var wire 1 ; in0 $end
$var wire 1 4 in1 $end
$var wire 1 < in2 $end
$var wire 1 = in3 $end
$var wire 2 G select [1:0] $end
$var wire 1 H w2 $end
$var wire 1 I w1 $end
$var wire 1 ? out $end
$scope module first_bottom $end
$var wire 1 < in0 $end
$var wire 1 = in1 $end
$var wire 1 J select $end
$var wire 1 H out $end
$upscope $end
$scope module first_top $end
$var wire 1 ; in0 $end
$var wire 1 4 in1 $end
$var wire 1 K select $end
$var wire 1 I out $end
$upscope $end
$scope module second $end
$var wire 1 I in0 $end
$var wire 1 H in1 $end
$var wire 1 L select $end
$var wire 1 ? out $end
$upscope $end
$upscope $end
$scope module mux3 $end
$var wire 1 @ in0 $end
$var wire 1 ? in1 $end
$var wire 1 M select $end
$var wire 1 7 out $end
$upscope $end
$upscope $end
$scope module EQ_select $end
$var wire 1 N in0 $end
$var wire 1 7 in1 $end
$var wire 1 1 select $end
$var wire 1 $ out $end
$upscope $end
$scope module GT_mux $end
$var wire 1 O in0 $end
$var wire 1 P in1 $end
$var wire 1 4 in2 $end
$var wire 1 Q in3 $end
$var wire 1 R in4 $end
$var wire 1 S in5 $end
$var wire 1 T in6 $end
$var wire 1 4 in7 $end
$var wire 3 U select [2:0] $end
$var wire 1 V w2 $end
$var wire 1 W w1 $end
$var wire 1 6 out $end
$scope module mux1 $end
$var wire 1 O in0 $end
$var wire 1 P in1 $end
$var wire 1 4 in2 $end
$var wire 1 Q in3 $end
$var wire 2 X select [1:0] $end
$var wire 1 Y w2 $end
$var wire 1 Z w1 $end
$var wire 1 W out $end
$scope module first_bottom $end
$var wire 1 4 in0 $end
$var wire 1 Q in1 $end
$var wire 1 [ select $end
$var wire 1 Y out $end
$upscope $end
$scope module first_top $end
$var wire 1 O in0 $end
$var wire 1 P in1 $end
$var wire 1 \ select $end
$var wire 1 Z out $end
$upscope $end
$scope module second $end
$var wire 1 Z in0 $end
$var wire 1 Y in1 $end
$var wire 1 ] select $end
$var wire 1 W out $end
$upscope $end
$upscope $end
$scope module mux2 $end
$var wire 1 R in0 $end
$var wire 1 S in1 $end
$var wire 1 T in2 $end
$var wire 1 4 in3 $end
$var wire 2 ^ select [1:0] $end
$var wire 1 _ w2 $end
$var wire 1 ` w1 $end
$var wire 1 V out $end
$scope module first_bottom $end
$var wire 1 T in0 $end
$var wire 1 4 in1 $end
$var wire 1 a select $end
$var wire 1 _ out $end
$upscope $end
$scope module first_top $end
$var wire 1 R in0 $end
$var wire 1 S in1 $end
$var wire 1 b select $end
$var wire 1 ` out $end
$upscope $end
$scope module second $end
$var wire 1 ` in0 $end
$var wire 1 _ in1 $end
$var wire 1 c select $end
$var wire 1 V out $end
$upscope $end
$upscope $end
$scope module mux3 $end
$var wire 1 W in0 $end
$var wire 1 V in1 $end
$var wire 1 d select $end
$var wire 1 6 out $end
$upscope $end
$upscope $end
$scope module GT_select $end
$var wire 1 6 in1 $end
$var wire 1 1 select $end
$var wire 1 # out $end
$var wire 1 . in0 $end
$upscope $end
$upscope $end
$scope module comp1 $end
$var wire 2 e A [1:0] $end
$var wire 2 f B [1:0] $end
$var wire 1 g notB0 $end
$var wire 3 h select [2:0] $end
$var wire 1 - preGT $end
$var wire 1 0 preEQ $end
$var wire 1 i GT_out $end
$var wire 1 . GT $end
$var wire 1 j EQ_out $end
$var wire 1 1 EQ $end
$scope module EQ_mux $end
$var wire 1 g in0 $end
$var wire 1 k in1 $end
$var wire 1 l in2 $end
$var wire 1 m in3 $end
$var wire 1 n in4 $end
$var wire 1 g in5 $end
$var wire 1 o in6 $end
$var wire 1 p in7 $end
$var wire 3 q select [2:0] $end
$var wire 1 r w2 $end
$var wire 1 s w1 $end
$var wire 1 j out $end
$scope module mux1 $end
$var wire 1 g in0 $end
$var wire 1 k in1 $end
$var wire 1 l in2 $end
$var wire 1 m in3 $end
$var wire 2 t select [1:0] $end
$var wire 1 u w2 $end
$var wire 1 v w1 $end
$var wire 1 s out $end
$scope module first_bottom $end
$var wire 1 l in0 $end
$var wire 1 m in1 $end
$var wire 1 w select $end
$var wire 1 u out $end
$upscope $end
$scope module first_top $end
$var wire 1 g in0 $end
$var wire 1 k in1 $end
$var wire 1 x select $end
$var wire 1 v out $end
$upscope $end
$scope module second $end
$var wire 1 v in0 $end
$var wire 1 u in1 $end
$var wire 1 y select $end
$var wire 1 s out $end
$upscope $end
$upscope $end
$scope module mux2 $end
$var wire 1 n in0 $end
$var wire 1 g in1 $end
$var wire 1 o in2 $end
$var wire 1 p in3 $end
$var wire 2 z select [1:0] $end
$var wire 1 { w2 $end
$var wire 1 | w1 $end
$var wire 1 r out $end
$scope module first_bottom $end
$var wire 1 o in0 $end
$var wire 1 p in1 $end
$var wire 1 } select $end
$var wire 1 { out $end
$upscope $end
$scope module first_top $end
$var wire 1 n in0 $end
$var wire 1 g in1 $end
$var wire 1 ~ select $end
$var wire 1 | out $end
$upscope $end
$scope module second $end
$var wire 1 | in0 $end
$var wire 1 { in1 $end
$var wire 1 !" select $end
$var wire 1 r out $end
$upscope $end
$upscope $end
$scope module mux3 $end
$var wire 1 s in0 $end
$var wire 1 r in1 $end
$var wire 1 "" select $end
$var wire 1 j out $end
$upscope $end
$upscope $end
$scope module EQ_select $end
$var wire 1 #" in0 $end
$var wire 1 j in1 $end
$var wire 1 0 select $end
$var wire 1 1 out $end
$upscope $end
$scope module GT_mux $end
$var wire 1 $" in0 $end
$var wire 1 %" in1 $end
$var wire 1 g in2 $end
$var wire 1 &" in3 $end
$var wire 1 '" in4 $end
$var wire 1 (" in5 $end
$var wire 1 )" in6 $end
$var wire 1 g in7 $end
$var wire 3 *" select [2:0] $end
$var wire 1 +" w2 $end
$var wire 1 ," w1 $end
$var wire 1 i out $end
$scope module mux1 $end
$var wire 1 $" in0 $end
$var wire 1 %" in1 $end
$var wire 1 g in2 $end
$var wire 1 &" in3 $end
$var wire 2 -" select [1:0] $end
$var wire 1 ." w2 $end
$var wire 1 /" w1 $end
$var wire 1 ," out $end
$scope module first_bottom $end
$var wire 1 g in0 $end
$var wire 1 &" in1 $end
$var wire 1 0" select $end
$var wire 1 ." out $end
$upscope $end
$scope module first_top $end
$var wire 1 $" in0 $end
$var wire 1 %" in1 $end
$var wire 1 1" select $end
$var wire 1 /" out $end
$upscope $end
$scope module second $end
$var wire 1 /" in0 $end
$var wire 1 ." in1 $end
$var wire 1 2" select $end
$var wire 1 ," out $end
$upscope $end
$upscope $end
$scope module mux2 $end
$var wire 1 '" in0 $end
$var wire 1 (" in1 $end
$var wire 1 )" in2 $end
$var wire 1 g in3 $end
$var wire 2 3" select [1:0] $end
$var wire 1 4" w2 $end
$var wire 1 5" w1 $end
$var wire 1 +" out $end
$scope module first_bottom $end
$var wire 1 )" in0 $end
$var wire 1 g in1 $end
$var wire 1 6" select $end
$var wire 1 4" out $end
$upscope $end
$scope module first_top $end
$var wire 1 '" in0 $end
$var wire 1 (" in1 $end
$var wire 1 7" select $end
$var wire 1 5" out $end
$upscope $end
$scope module second $end
$var wire 1 5" in0 $end
$var wire 1 4" in1 $end
$var wire 1 8" select $end
$var wire 1 +" out $end
$upscope $end
$upscope $end
$scope module mux3 $end
$var wire 1 ," in0 $end
$var wire 1 +" in1 $end
$var wire 1 9" select $end
$var wire 1 i out $end
$upscope $end
$upscope $end
$scope module GT_select $end
$var wire 1 i in1 $end
$var wire 1 0 select $end
$var wire 1 . out $end
$var wire 1 - in0 $end
$upscope $end
$upscope $end
$scope module comp2 $end
$var wire 2 :" A [1:0] $end
$var wire 2 ;" B [1:0] $end
$var wire 1 <" notB0 $end
$var wire 3 =" select [2:0] $end
$var wire 1 , preGT $end
$var wire 1 / preEQ $end
$var wire 1 >" GT_out $end
$var wire 1 - GT $end
$var wire 1 ?" EQ_out $end
$var wire 1 0 EQ $end
$scope module EQ_mux $end
$var wire 1 <" in0 $end
$var wire 1 @" in1 $end
$var wire 1 A" in2 $end
$var wire 1 B" in3 $end
$var wire 1 C" in4 $end
$var wire 1 <" in5 $end
$var wire 1 D" in6 $end
$var wire 1 E" in7 $end
$var wire 3 F" select [2:0] $end
$var wire 1 G" w2 $end
$var wire 1 H" w1 $end
$var wire 1 ?" out $end
$scope module mux1 $end
$var wire 1 <" in0 $end
$var wire 1 @" in1 $end
$var wire 1 A" in2 $end
$var wire 1 B" in3 $end
$var wire 2 I" select [1:0] $end
$var wire 1 J" w2 $end
$var wire 1 K" w1 $end
$var wire 1 H" out $end
$scope module first_bottom $end
$var wire 1 A" in0 $end
$var wire 1 B" in1 $end
$var wire 1 L" select $end
$var wire 1 J" out $end
$upscope $end
$scope module first_top $end
$var wire 1 <" in0 $end
$var wire 1 @" in1 $end
$var wire 1 M" select $end
$var wire 1 K" out $end
$upscope $end
$scope module second $end
$var wire 1 K" in0 $end
$var wire 1 J" in1 $end
$var wire 1 N" select $end
$var wire 1 H" out $end
$upscope $end
$upscope $end
$scope module mux2 $end
$var wire 1 C" in0 $end
$var wire 1 <" in1 $end
$var wire 1 D" in2 $end
$var wire 1 E" in3 $end
$var wire 2 O" select [1:0] $end
$var wire 1 P" w2 $end
$var wire 1 Q" w1 $end
$var wire 1 G" out $end
$scope module first_bottom $end
$var wire 1 D" in0 $end
$var wire 1 E" in1 $end
$var wire 1 R" select $end
$var wire 1 P" out $end
$upscope $end
$scope module first_top $end
$var wire 1 C" in0 $end
$var wire 1 <" in1 $end
$var wire 1 S" select $end
$var wire 1 Q" out $end
$upscope $end
$scope module second $end
$var wire 1 Q" in0 $end
$var wire 1 P" in1 $end
$var wire 1 T" select $end
$var wire 1 G" out $end
$upscope $end
$upscope $end
$scope module mux3 $end
$var wire 1 H" in0 $end
$var wire 1 G" in1 $end
$var wire 1 U" select $end
$var wire 1 ?" out $end
$upscope $end
$upscope $end
$scope module EQ_select $end
$var wire 1 V" in0 $end
$var wire 1 ?" in1 $end
$var wire 1 / select $end
$var wire 1 0 out $end
$upscope $end
$scope module GT_mux $end
$var wire 1 W" in0 $end
$var wire 1 X" in1 $end
$var wire 1 <" in2 $end
$var wire 1 Y" in3 $end
$var wire 1 Z" in4 $end
$var wire 1 [" in5 $end
$var wire 1 \" in6 $end
$var wire 1 <" in7 $end
$var wire 3 ]" select [2:0] $end
$var wire 1 ^" w2 $end
$var wire 1 _" w1 $end
$var wire 1 >" out $end
$scope module mux1 $end
$var wire 1 W" in0 $end
$var wire 1 X" in1 $end
$var wire 1 <" in2 $end
$var wire 1 Y" in3 $end
$var wire 2 `" select [1:0] $end
$var wire 1 a" w2 $end
$var wire 1 b" w1 $end
$var wire 1 _" out $end
$scope module first_bottom $end
$var wire 1 <" in0 $end
$var wire 1 Y" in1 $end
$var wire 1 c" select $end
$var wire 1 a" out $end
$upscope $end
$scope module first_top $end
$var wire 1 W" in0 $end
$var wire 1 X" in1 $end
$var wire 1 d" select $end
$var wire 1 b" out $end
$upscope $end
$scope module second $end
$var wire 1 b" in0 $end
$var wire 1 a" in1 $end
$var wire 1 e" select $end
$var wire 1 _" out $end
$upscope $end
$upscope $end
$scope module mux2 $end
$var wire 1 Z" in0 $end
$var wire 1 [" in1 $end
$var wire 1 \" in2 $end
$var wire 1 <" in3 $end
$var wire 2 f" select [1:0] $end
$var wire 1 g" w2 $end
$var wire 1 h" w1 $end
$var wire 1 ^" out $end
$scope module first_bottom $end
$var wire 1 \" in0 $end
$var wire 1 <" in1 $end
$var wire 1 i" select $end
$var wire 1 g" out $end
$upscope $end
$scope module first_top $end
$var wire 1 Z" in0 $end
$var wire 1 [" in1 $end
$var wire 1 j" select $end
$var wire 1 h" out $end
$upscope $end
$scope module second $end
$var wire 1 h" in0 $end
$var wire 1 g" in1 $end
$var wire 1 k" select $end
$var wire 1 ^" out $end
$upscope $end
$upscope $end
$scope module mux3 $end
$var wire 1 _" in0 $end
$var wire 1 ^" in1 $end
$var wire 1 l" select $end
$var wire 1 >" out $end
$upscope $end
$upscope $end
$scope module GT_select $end
$var wire 1 >" in1 $end
$var wire 1 / select $end
$var wire 1 - out $end
$var wire 1 , in0 $end
$upscope $end
$upscope $end
$scope module comp3 $end
$var wire 2 m" A [1:0] $end
$var wire 2 n" B [1:0] $end
$var wire 1 o" notB0 $end
$var wire 1 " preEQ $end
$var wire 1 ! preGT $end
$var wire 3 p" select [2:0] $end
$var wire 1 q" GT_out $end
$var wire 1 , GT $end
$var wire 1 r" EQ_out $end
$var wire 1 / EQ $end
$scope module EQ_mux $end
$var wire 1 o" in0 $end
$var wire 1 s" in1 $end
$var wire 1 t" in2 $end
$var wire 1 u" in3 $end
$var wire 1 v" in4 $end
$var wire 1 o" in5 $end
$var wire 1 w" in6 $end
$var wire 1 x" in7 $end
$var wire 3 y" select [2:0] $end
$var wire 1 z" w2 $end
$var wire 1 {" w1 $end
$var wire 1 r" out $end
$scope module mux1 $end
$var wire 1 o" in0 $end
$var wire 1 s" in1 $end
$var wire 1 t" in2 $end
$var wire 1 u" in3 $end
$var wire 2 |" select [1:0] $end
$var wire 1 }" w2 $end
$var wire 1 ~" w1 $end
$var wire 1 {" out $end
$scope module first_bottom $end
$var wire 1 t" in0 $end
$var wire 1 u" in1 $end
$var wire 1 !# select $end
$var wire 1 }" out $end
$upscope $end
$scope module first_top $end
$var wire 1 o" in0 $end
$var wire 1 s" in1 $end
$var wire 1 "# select $end
$var wire 1 ~" out $end
$upscope $end
$scope module second $end
$var wire 1 ~" in0 $end
$var wire 1 }" in1 $end
$var wire 1 ## select $end
$var wire 1 {" out $end
$upscope $end
$upscope $end
$scope module mux2 $end
$var wire 1 v" in0 $end
$var wire 1 o" in1 $end
$var wire 1 w" in2 $end
$var wire 1 x" in3 $end
$var wire 2 $# select [1:0] $end
$var wire 1 %# w2 $end
$var wire 1 &# w1 $end
$var wire 1 z" out $end
$scope module first_bottom $end
$var wire 1 w" in0 $end
$var wire 1 x" in1 $end
$var wire 1 '# select $end
$var wire 1 %# out $end
$upscope $end
$scope module first_top $end
$var wire 1 v" in0 $end
$var wire 1 o" in1 $end
$var wire 1 (# select $end
$var wire 1 &# out $end
$upscope $end
$scope module second $end
$var wire 1 &# in0 $end
$var wire 1 %# in1 $end
$var wire 1 )# select $end
$var wire 1 z" out $end
$upscope $end
$upscope $end
$scope module mux3 $end
$var wire 1 {" in0 $end
$var wire 1 z" in1 $end
$var wire 1 *# select $end
$var wire 1 r" out $end
$upscope $end
$upscope $end
$scope module EQ_select $end
$var wire 1 +# in0 $end
$var wire 1 r" in1 $end
$var wire 1 " select $end
$var wire 1 / out $end
$upscope $end
$scope module GT_mux $end
$var wire 1 ,# in0 $end
$var wire 1 -# in1 $end
$var wire 1 o" in2 $end
$var wire 1 .# in3 $end
$var wire 1 /# in4 $end
$var wire 1 0# in5 $end
$var wire 1 1# in6 $end
$var wire 1 o" in7 $end
$var wire 3 2# select [2:0] $end
$var wire 1 3# w2 $end
$var wire 1 4# w1 $end
$var wire 1 q" out $end
$scope module mux1 $end
$var wire 1 ,# in0 $end
$var wire 1 -# in1 $end
$var wire 1 o" in2 $end
$var wire 1 .# in3 $end
$var wire 2 5# select [1:0] $end
$var wire 1 6# w2 $end
$var wire 1 7# w1 $end
$var wire 1 4# out $end
$scope module first_bottom $end
$var wire 1 o" in0 $end
$var wire 1 .# in1 $end
$var wire 1 8# select $end
$var wire 1 6# out $end
$upscope $end
$scope module first_top $end
$var wire 1 ,# in0 $end
$var wire 1 -# in1 $end
$var wire 1 9# select $end
$var wire 1 7# out $end
$upscope $end
$scope module second $end
$var wire 1 7# in0 $end
$var wire 1 6# in1 $end
$var wire 1 :# select $end
$var wire 1 4# out $end
$upscope $end
$upscope $end
$scope module mux2 $end
$var wire 1 /# in0 $end
$var wire 1 0# in1 $end
$var wire 1 1# in2 $end
$var wire 1 o" in3 $end
$var wire 2 ;# select [1:0] $end
$var wire 1 <# w2 $end
$var wire 1 =# w1 $end
$var wire 1 3# out $end
$scope module first_bottom $end
$var wire 1 1# in0 $end
$var wire 1 o" in1 $end
$var wire 1 ># select $end
$var wire 1 <# out $end
$upscope $end
$scope module first_top $end
$var wire 1 /# in0 $end
$var wire 1 0# in1 $end
$var wire 1 ?# select $end
$var wire 1 =# out $end
$upscope $end
$scope module second $end
$var wire 1 =# in0 $end
$var wire 1 <# in1 $end
$var wire 1 @# select $end
$var wire 1 3# out $end
$upscope $end
$upscope $end
$scope module mux3 $end
$var wire 1 4# in0 $end
$var wire 1 3# in1 $end
$var wire 1 A# select $end
$var wire 1 q" out $end
$upscope $end
$upscope $end
$scope module GT_select $end
$var wire 1 ! in0 $end
$var wire 1 q" in1 $end
$var wire 1 " select $end
$var wire 1 , out $end
$upscope $end
$upscope $end
$upscope $end
$upscope $end
$enddefinitions $end
#0
$dumpvars
1A#
0@#
1?#
1>#
0=#
1<#
b1 ;#
0:#
19#
18#
07#
06#
b1 5#
04#
03#
b101 2#
11#
00#
1/#
0.#
0-#
0,#
0+#
1*#
0)#
1(#
1'#
1&#
0%#
b1 $#
0##
1"#
1!#
0~"
0}"
b1 |"
0{"
1z"
b101 y"
0x"
0w"
0v"
0u"
0t"
0s"
1r"
0q"
b101 p"
1o"
b10 n"
b10 m"
1l"
1k"
1j"
1i"
0h"
0g"
b11 f"
1e"
1d"
1c"
0b"
0a"
b11 `"
0_"
0^"
b111 ]"
1\"
0["
1Z"
0Y"
0X"
0W"
0V"
1U"
1T"
1S"
1R"
0Q"
1P"
b11 O"
1N"
1M"
1L"
0K"
0J"
b11 I"
0H"
1G"
b111 F"
1E"
0D"
0C"
0B"
1A"
0@"
1?"
0>"
b111 ="
0<"
b11 ;"
b11 :"
19"
08"
17"
16"
05"
14"
b1 3"
02"
11"
10"
0/"
0."
b1 -"
0,"
0+"
b101 *"
1)"
0("
1'"
0&"
0%"
0$"
0#"
1""
0!"
1~
1}
1|
0{
b1 z
0y
1x
1w
0v
0u
b1 t
0s
1r
b101 q
0p
0o
0n
0m
0l
0k
1j
0i
b101 h
1g
b10 f
b10 e
0d
1c
0b
0a
1`
1_
b10 ^
1]
0\
0[
0Z
0Y
b10 X
0W
1V
b10 U
1T
0S
1R
0Q
0P
0O
0N
0M
1L
0K
0J
0I
0H
b10 G
1F
0E
0D
0C
1B
b10 A
1@
0?
b10 >
1=
0<
0;
0:
19
08
17
06
b10 5
04
b1 3
b1 2
01
00
0/
0.
0-
0,
b10111001 +
b10111001 *
b0 )
b10111001 (
b10111001 '
b10111001 &
b10111001 %
0$
0#
0"
0!
$end
#200
1#
1.
1-
1,
1!
b1 )
#400
1$
0#
11
0.
10
0-
1/
0,
0!
1"
b10 )
#600
1!
b11 )
#800
0$
01
00
0/
0!
0"
b100 )
#1000
1s
0r
1+"
0@
1?
0V
1v
0|
1."
15"
0B
1H
0`
0_
0r"
1q"
1Q"
1g"
0x
0w
0~
0}
01"
00"
07"
06"
1E
1D
1K
1J
1\
1[
1b
1a
0z"
13#
1G"
1<"
0P"
b0 t
b0 z
b0 -"
b0 3"
b11 A
b11 G
b11 X
b11 ^
1##
1)#
1:#
1@#
0N"
0T"
0?"
0e"
0k"
1j
17
06
0A"
0E"
b11 |"
b11 $#
b11 5#
b11 ;#
b1 I"
b1 O"
0U"
b1 `"
b1 f"
0l"
0""
09"
1M
1d
b10 ;"
b0 f
b11 3
b111 p"
b111 y"
b111 2#
b11 m"
b1 ="
b1 F"
b1 ]"
b0 :"
b0 h
b0 q
b0 *"
b0 e
b111 5
b111 >
b111 U
b11 2
b10100011 %
b10100011 +
b11000011 &
b11000011 *
b0 )
b10100011 (
b11000011 '
#1200
1#
1.
1-
1,
1!
b1 )
#1400
0!
1"
b10 )
#1600
1!
b11 )
#1800
0#
0.
0-
0,
0!
0"
b100 )
#2000
1?"
1H"
0G"
1@
0?
1V
1}"
1=#
1J"
1h"
0s
1B
0H
1`
1_
0"#
0!#
0(#
0'#
09#
08#
0?#
0>#
0&#
1<#
0M"
0L"
0S"
0R"
0d"
0c"
0j"
0i"
0Q"
1g"
0v
0."
0E
0D
0K
0J
0\
0[
0b
0a
0z"
13#
1^"
0o"
0%#
0<"
0P"
0g
1u
b10 A
b10 G
b10 X
b10 ^
0##
0)#
0:#
0@#
0q"
1N"
1T"
1e"
1k"
0j
1i
17
1t"
1x"
1A"
1E"
1l
1p
b0 |"
b0 $#
0*#
b0 5#
b0 ;#
0A#
b10 I"
b10 O"
b10 `"
b10 f"
1""
19"
0M
0d
b1 n"
b1 ;"
b1 f
b1 3
b0 p"
b0 y"
b0 2#
b0 m"
b10 ="
b10 F"
b10 ]"
b1 :"
b100 h
b100 q
b100 *"
b10 e
b10 5
b10 >
b10 U
b1 2
b1010101 %
b1010101 +
b11001 &
b11001 *
b0 )
b1010101 (
b11001 '
#2200
1#
1.
1-
1,
1!
b1 )
#2400
0#
0.
0-
0,
0!
1"
b10 )
#2600
1!
b11 )
#2800
0!
0"
b100 )
